su.password-0.1.2-py3.6-nspkg.pth
su/password.py
su.password-0.1.2.dist-info/DESCRIPTION.rst
su.password-0.1.2.dist-info/METADATA
su.password-0.1.2.dist-info/RECORD
su.password-0.1.2.dist-info/WHEEL
su.password-0.1.2.dist-info/metadata.json
su.password-0.1.2.dist-info/namespace_packages.txt
su.password-0.1.2.dist-info/top_level.txt
