Metadata-Version: 2.0
Name: su.password
Version: 0.1.2
Summary: A simple password management lib.
Home-page: https://github.com/zhaolins/su.password
Author: Zhaolin Su
Author-email: z@suho.me
License: MIT
Keywords: development
Platform: UNKNOWN
Classifier: Development Status :: 4 - Beta
Classifier: Intended Audience :: Developers
Classifier: Topic :: Software Development :: Libraries
Classifier: License :: OSI Approved :: MIT License
Classifier: Programming Language :: Python :: 3.6
Requires-Dist: setuptools
Requires-Dist: su.aes
